{"pesi":{"AAVEBNB":"0; (0%); 0%","ADABNB":"0; (0%); 0%","ALGOBNB":"0; (0%); 0%","ALPHABNB":"0; (0%); 0%","ANKRBNB":"0; (0%); 0%","ANTBNB":"0; (0%); 0%","ARPABNB":"0; (0%); 0%","ATOMBNB":"0; (0%); 0%","AVABNB":"0; (0%); 0%","AVAXBNB":"0; (0%); 0%","AXSBNB":"0; (0%); 0%","BAKEBNB":"0.07713281886725509; (7.71%); -2.07%","BANDBNB":"0; (0%); 0%","BATBNB":"0; (0%); 0%","BCHBNB":"0; (0%); 0%","BELBNB":"0; (0%); 0%","BIFIBNB":"0; (0%); 0%","BLZBNB":"0; (0%); 0%","BTTBNB":"0.0366267893110367; (3.66%); 0.43%","BURGERBNB":"0.04772091206795598; (4.77%); 3.16%","CAKEBNB":"0.3524030536544144; (35.24%); -0.77%","CELRBNB":"0; (0%); 0%","CHRBNB":"0; (0%); 0%","CHZBNB":"0; (0%); 0%","COCOSBNB":"0; (0%); 0%","COSBNB":"0; (0%); 0%","COTIBNB":"0; (0%); 0%","CREAMBNB":"0; (0%); 0%","CRVBNB":"0; (0%); 0%","CTKBNB":"0; (0%); 0%","CTSIBNB":"0.0063311808928633775; (0.63%); -1.47%","DASHBNB":"0; (0%); 0%","DGBBNB":"0; (0%); 0%","DIABNB":"0; (0%); 0%","DOTBNB":"0; (0%); 0%","EGLDBNB":"0; (0%); 0%","ENJBNB":"0; (0%); 0%","EOSBNB":"0; (0%); 0%","ETCBNB":"0.26057319534028694; (26.06%); 1.02%","FETBNB":"0; (0%); 0%","FILBNB":"0; (0%); 0%","FIOBNB":"0; (0%); 0%","FTMBNB":"0; (0%); 0%","FTTBNB":"0; (0%); 0%","HARDBNB":"0; (0%); 0%","HBARBNB":"0; (0%); 0%","HOTBNB":"0; (0%); 0%","ICXBNB":"0; (0%); 0%","INJBNB":"0; (0%); 0%","IOSTBNB":"0; (0%); 0%","IOTABNB":"0; (0%); 0%","IQBNB":"0; (0%); 0%","JSTBNB":"0; (0%); 0%","KAVABNB":"0; (0%); 0%","KP3RBNB":"0; (0%); 0%","KSMBNB":"0; (0%); 0%","LTCBNB":"0; (0%); 0%","LUNABNB":"0; (0%); 0%","MATICBNB":"0; (0%); 0%","MBLBNB":"0; (0%); 0%","MFTBNB":"0; (0%); 0%","MITHBNB":"0; (0%); 0%","MKRBNB":"0; (0%); 0%","NEARBNB":"0; (0%); 0%","NEOBNB":"0; (0%); 0%","NMRBNB":"0; (0%); 0%","OCEANBNB":"0; (0%); 0%","OGNBNB":"0; (0%); 0%","ONEBNB":"0; (0%); 0%","ONTBNB":"0; (0%); 0%","PAXGBNB":"0; (0%); 0%","PERLBNB":"0; (0%); 0%","PROMBNB":"0.02163259160854529; (2.16%); -0.1%","RSRBNB":"0; (0%); 0%","RUNEBNB":"0.03424221582938344; (3.42%); 0.1%","RVNBNB":"0; (0%); 0%","SANDBNB":"0; (0%); 0%","SCBNB":"0; (0%); 0%","SNXBNB":"0; (0%); 0%","SOLBNB":"0; (0%); 0%","SPARTABNB":"0; (0%); 0%","SRMBNB":"0; (0%); 0%","STMXBNB":"0; (0%); 0%","STXBNB":"0; (0%); 0%","SUSHIBNB":"0; (0%); 0%","SWRVBNB":"0; (0%); 0%","SXPBNB":"0; (0%); 0%","THETABNB":"0; (0%); 0%","TROYBNB":"0; (0%); 0%","TRXBNB":"0; (0%); 0%","UNFIBNB":"0; (0%); 0%","UNIBNB":"0; (0%); 0%","VETBNB":"0; (0%); 0%","VTHOBNB":"0; (0%); 0%","WABIBNB":"0; (0%); 0%","WANBNB":"0; (0%); 0%","WAVESBNB":"0.0414744064051363; (4.15%); -0.32%","WINBNB":"0.054784214408664635; (5.48%); -0.16%","WINGBNB":"0; (0%); 0%","WNXMBNB":"0; (0%); 0%","WRXBNB":"0.06707862161445777; (6.71%); 0.18%","WTCBNB":"0; (0%); 0%","XLMBNB":"0; (0%); 0%","XMRBNB":"0; (0%); 0%","XRPBNB":"0; (0%); 0%","XTZBNB":"0; (0%); 0%","XVSBNB":"0; (0%); 0%","YFIBNB":"0; (0%); 0%","YFIIBNB":"0; (0%); 0%","ZECBNB":"0; (0%); 0%","ZENBNB":"0; (0%); 0%","ZILBNB":"0; (0%); 0%"},"rendimento_atteso":0.003156398025913858,"deviazione_standard":0.01978918798853263,"sharpe_ratio":0.15950113909387875}