{"weights":{"1INCHDOWNUSDT":0.011867967893400156,"1INCHUPUSDT":0,"1INCHUSDT":0,"AAVEDOWNUSDT":0.05388046108231841,"AAVEUPUSDT":0,"AAVEUSDT":0,"ADADOWNUSDT":0.07209531765132196,"ADAUPUSDT":0,"ADAUSDT":0,"AIONUSDT":0,"AKROUSDT":0,"ALGOUSDT":0,"ALICEUSDT":0,"ALPHAUSDT":0,"ANKRUSDT":0,"ANTUSDT":0,"ARDRUSDT":0,"ARPAUSDT":0,"ARUSDT":0.021949137050167055,"ATAUSDT":0,"ATOMUSDT":0,"AUDIOUSDT":0,"AUDUSDT":0,"AUTOUSDT":0,"AVAUSDT":0,"AVAXUSDT":0,"AXSUSDT":0,"BADGERUSDT":0,"BAKEUSDT":0,"BALUSDT":0,"BANDUSDT":0,"BATUSDT":0,"BCHDOWNUSDT":0,"BCHUPUSDT":0,"BCHUSDT":0,"BEAMUSDT":0,"BELUSDT":0,"BLZUSDT":0,"BNBDOWNUSDT":0.02356829761730816,"BNBUPUSDT":0,"BNBUSDT":0,"BNTUSDT":0,"BTCDOWNUSDT":0,"BTCSTUSDT":0,"BTCUPUSDT":0,"BTCUSDT":0,"BTGUSDT":0.030172445588323868,"BTSUSDT":0,"BTTUSDT":0,"BURGERUSDT":0.04091612371165936,"BZRXUSDT":0,"CAKEUSDT":0,"CELOUSDT":0,"CELRUSDT":0,"CFXUSDT":0,"CHRUSDT":0,"CHZUSDT":0,"CKBUSDT":0.0024225582893831303,"COCOSUSDT":0,"COMPUSDT":0,"COSUSDT":0,"COTIUSDT":0,"CRVUSDT":0,"CTKUSDT":0,"CTSIUSDT":0,"CTXCUSDT":0,"CVCUSDT":0,"DASHUSDT":0,"DATAUSDT":0.056738338599723104,"DCRUSDT":0,"DEGOUSDT":0,"DENTUSDT":0,"DGBUSDT":0,"DIAUSDT":0,"DNTUSDT":0,"DOCKUSDT":0.003660859875166036,"DODOUSDT":0,"DOGEUSDT":0,"DOTDOWNUSDT":0.004189074777668658,"DOTUPUSDT":0,"DOTUSDT":0,"DREPUSDT":0,"DUSKUSDT":0,"EGLDUSDT":0,"ENJUSDT":0,"EOSDOWNUSDT":0.007780443277041723,"EOSUPUSDT":0,"EOSUSDT":0,"EPSUSDT":0,"ETCUSDT":0,"ETHDOWNUSDT":0.021321266239872877,"ETHUPUSDT":0,"ETHUSDT":0,"EURUSDT":0,"FETUSDT":0,"FILDOWNUSDT":0.036583725240403986,"FILUPUSDT":0,"FILUSDT":0,"FIOUSDT":0.024057155966513304,"FIROUSDT":0,"FISUSDT":0,"FLMUSDT":0,"FORTHUSDT":0,"FTMUSDT":0,"FTTUSDT":0,"FUNUSDT":0,"GBPUSDT":0,"GRTUSDT":0,"GTOUSDT":0.028584893911696767,"GXSUSDT":0,"HARDUSDT":0.056696267693608596,"HBARUSDT":0,"HIVEUSDT":0,"HNTUSDT":0,"HOTUSDT":0,"ICPUSDT":0,"ICXUSDT":0,"INJUSDT":0,"IOSTUSDT":0,"IOTAUSDT":0,"IOTXUSDT":0,"IRISUSDT":0,"JSTUSDT":0,"KAVAUSDT":0,"KEYUSDT":0.012252131850042619,"KMDUSDT":0,"KNCUSDT":0,"KSMUSDT":0.10003040971193389,"LINAUSDT":0,"LINKDOWNUSDT":0.004944334030548251,"LINKUPUSDT":0,"LINKUSDT":0,"LITUSDT":0,"LPTUSDT":0,"LRCUSDT":0,"LSKUSDT":0,"LTCDOWNUSDT":0,"LTCUPUSDT":0,"LTCUSDT":0,"LTOUSDT":0.0629087391496348,"LUNAUSDT":0,"MANAUSDT":0,"MASKUSDT":0,"MATICUSDT":0,"MBLUSDT":0,"MDTUSDT":0.011071980795132389,"MDXUSDT":0,"MFTUSDT":0.009538462424338473,"MIRUSDT":0,"MITHUSDT":0.03681536913474534,"MKRUSDT":0,"MTLUSDT":0,"NANOUSDT":0,"NBSUSDT":0,"NEARUSDT":0.019099864725381485,"NEOUSDT":0,"NKNUSDT":0,"NMRUSDT":0,"NULSUSDT":0,"NUUSDT":0,"OCEANUSDT":0,"OGNUSDT":0,"OMGUSDT":0,"OMUSDT":0,"ONEUSDT":0,"ONGUSDT":0,"ONTUSDT":0,"ORNUSDT":0.005962201191224833,"OXTUSDT":0,"PAXGUSDT":0,"PERLUSDT":0,"PERPUSDT":0,"PNTUSDT":0,"POLSUSDT":0,"PONDUSDT":0,"PUNDIXUSDT":0,"QTUMUSDT":0,"RAMPUSDT":0,"REEFUSDT":0,"RENUSDT":0,"REPUSDT":0,"RIFUSDT":0,"RLCUSDT":0,"ROSEUSDT":0,"RSRUSDT":0,"RUNEUSDT":0,"RVNUSDT":0,"SANDUSDT":0,"SCUSDT":0,"SFPUSDT":0,"SHIBUSDT":0,"SKLUSDT":0,"SLPUSDT":0.027127183429938917,"SNXUSDT":0,"SOLUSDT":0,"SRMUSDT":0,"STMXUSDT":0,"STORJUSDT":0,"STPTUSDT":0.011672439293344657,"STRAXUSDT":0,"STXUSDT":0,"SUNUSDT":0,"SUPERUSDT":0,"SUSHIDOWNUSDT":0.030291446836619024,"SUSHIUPUSDT":0,"SUSHIUSDT":0,"SXPDOWNUSDT":0,"SXPUPUSDT":0,"SXPUSDT":0,"TCTUSDT":0.010324174137526586,"TFUELUSDT":0.05268824036385121,"THETAUSDT":0,"TKOUSDT":0,"TLMUSDT":0,"TOMOUSDT":0,"TRBUSDT":0,"TROYUSDT":0,"TRUUSDT":0,"TRXDOWNUSDT":0,"TRXUPUSDT":0,"TRXUSDT":0,"TWTUSDT":0,"UMAUSDT":0,"UNFIUSDT":0,"UNIDOWNUSDT":0.01628302580002175,"UNIUPUSDT":0,"UNIUSDT":0,"UTKUSDT":0,"VETUSDT":0,"VITEUSDT":0,"VTHOUSDT":0,"WANUSDT":0,"WAVESUSDT":0,"WINGUSDT":0,"WINUSDT":0,"WNXMUSDT":0,"WRXUSDT":0,"WTCUSDT":0,"XEMUSDT":0,"XLMDOWNUSDT":0,"XLMUPUSDT":0,"XLMUSDT":0,"XMRUSDT":0,"XRPDOWNUSDT":0.04972778229726173,"XRPUPUSDT":0,"XRPUSDT":0,"XTZDOWNUSDT":0.041516024903900266,"XTZUPUSDT":0,"XTZUSDT":0,"XVGUSDT":0,"XVSUSDT":0,"YFIDOWNUSDT":0.0012618554589765092,"YFIIUSDT":0,"YFIUPUSDT":0,"YFIUSDT":0,"ZECUSDT":0,"ZENUSDT":0,"ZILUSDT":0,"ZRXUSDT":0},"numerosità_campione":899,"expected_return":0.0003502005367015041,"standard_deviation":0.001979622598321271,"sharpe_ratio":0.17690267680237423}