{"pesi":{"1INCHBTC":"0; (0%); 0%","AAVEBTC":"0.0310239505442889; (3.1%); 2.06%","ACMBTC":"0.00578173327478183; (0.58%); -0.05%","ADABTC":"0.06979602463084866; (6.98%); 1.59%","ADXBTC":"0; (0%); 0%","AERGOBTC":"0; (0%); 0%","AGIBTC":"0; (0%); 0%","AIONBTC":"0; (0%); 0%","AKROBTC":"0; (0%); 0%","ALGOBTC":"0.02241523318820257; (2.24%); 2.24%","ALICEBTC":"0; (0%); 0%","ALPHABTC":"0.03005875630550279; (3.01%); 0.18%","AMBBTC":"0; (0%); -1.09%","ANKRBTC":"0; (0%); 0%","ANTBTC":"0; (0%); 0%","APPCBTC":"0; (0%); 0%","ARDRBTC":"0; (0%); 0%","ARKBTC":"0; (0%); 0%","ARPABTC":"0; (0%); 0%","ASRBTC":"0.003937751566295396; (0.39%); 0.08%","ASTBTC":"0; (0%); 0%","ATMBTC":"0.0173262815953319; (1.73%); 0.16%","ATOMBTC":"0; (0%); 0%","AUCTIONBTC":"0.004283217200261881; (0.43%); 0.43%","AUDIOBTC":"0; (0%); 0%","AUTOBTC":"0.014892332023033136; (1.49%); 0.82%","AVABTC":"0.012949991499498669; (1.29%); 0.22%","AVAXBTC":"0; (0%); 0%","AXSBTC":"0; (0%); 0%","BADGERBTC":"0; (0%); -0.14%","BALBTC":"0; (0%); 0%","BANDBTC":"0; (0%); 0%","BARBTC":"0; (0%); 0%","BATBTC":"0; (0%); 0%","BCDBTC":"0; (0%); 0%","BCHBTC":"0; (0%); 0%","BEAMBTC":"0.006481101395344803; (0.65%); -0.47%","BELBTC":"0; (0%); 0%","BLZBTC":"0; (0%); 0%","BNBBTC":"0; (0%); 0%","BNTBTC":"0; (0%); 0%","BQXBTC":"0; (0%); 0%","BRDBTC":"0; (0%); 0%","BTCSTBTC":"0; (0%); 0%","BTGBTC":"0; (0%); 0%","BTSBTC":"0; (0%); 0%","BZRXBTC":"0; (0%); 0%","CAKEBTC":"0; (0%); 0%","CDTBTC":"0; (0%); 0%","CELOBTC":"0; (0%); 0%","CELRBTC":"0; (0%); 0%","CFXBTC":"0; (0%); 0%","CHRBTC":"0.009790075967508072; (0.98%); 0.39%","CHZBTC":"0.005354393687400332; (0.54%); 0.54%","CKBBTC":"0; (0%); 0%","CNDBTC":"0; (0%); 0%","COMPBTC":"0; (0%); 0%","COSBTC":"0; (0%); 0%","COTIBTC":"0; (0%); 0%","CRVBTC":"0.012784019189733976; (1.28%); 0.97%","CTKBTC":"0; (0%); 0%","CTSIBTC":"0; (0%); 0%","CTXCBTC":"0; (0%); 0%","CVCBTC":"0; (0%); 0%","DASHBTC":"0.002140763516952828; (0.21%); 0.21%","DATABTC":"0; (0%); 0%","DCRBTC":"0.010937518514914563; (1.09%); -5.08%","DEGOBTC":"0; (0%); 0%","DGBBTC":"0; (0%); 0%","DIABTC":"0; (0%); 0%","DLTBTC":"0; (0%); -0.85%","DNTBTC":"0.008041743279596532; (0.8%); 0.8%","DOCKBTC":"0; (0%); 0%","DODOBTC":"0; (0%); 0%","DOGEBTC":"0; (0%); 0%","DOTBTC":"0.0027865476874529356; (0.28%); 0.28%","DREPBTC":"0; (0%); 0%","DUSKBTC":"0; (0%); 0%","EGLDBTC":"0; (0%); 0%","ELFBTC":"0; (0%); 0%","ENJBTC":"0; (0%); 0%","EOSBTC":"0.01221820004294631; (1.22%); 0.14%","EPSBTC":"0; (0%); 0%","ETCBTC":"0; (0%); 0%","ETHBTC":"0; (0%); 0%","EVXBTC":"0.04475530214350513; (4.48%); 3.3%","EZBTC":"0.007760328224515809; (0.78%); -0.52%","FETBTC":"0; (0%); 0%","FILBTC":"0; (0%); 0%","FIOBTC":"0; (0%); -0.1%","FIROBTC":"0; (0%); 0%","FISBTC":"0; (0%); 0%","FLMBTC":"0; (0%); 0%","FORBTC":"0.023774172236906727; (2.38%); 1.36%","FORTHBTC":"0.0015387992548473153; (0.15%); -0.67%","FRONTBTC":"0; (0%); 0%","FTMBTC":"0; (0%); 0%","FTTBTC":"0; (0%); 0%","FUNBTC":"0.004609886137487111; (0.46%); 0.37%","FXSBTC":"0; (0%); 0%","GASBTC":"0; (0%); 0%","GLMBTC":"0; (0%); 0%","GOBTC":"0; (0%); -0.7%","GRSBTC":"0; (0%); 0%","GRTBTC":"0; (0%); -1.46%","GTOBTC":"0; (0%); 0%","GVTBTC":"0; (0%); 0%","GXSBTC":"0.004059997808290574; (0.41%); -0.21%","HARDBTC":"0; (0%); 0%","HBARBTC":"0; (0%); 0%","HIVEBTC":"0; (0%); 0%","HNTBTC":"0; (0%); 0%","ICPBTC":"0; (0%); 0%","ICXBTC":"0; (0%); 0%","IDEXBTC":"0; (0%); 0%","INJBTC":"0; (0%); -0.32%","IOSTBTC":"0; (0%); 0%","IOTABTC":"0; (0%); 0%","IOTXBTC":"0.002783494361579796; (0.28%); -0.49%","IRISBTC":"0.005009815639460631; (0.5%); -0.56%","JSTBTC":"0; (0%); 0%","JUVBTC":"0.009188534772557197; (0.92%); 0.07%","KAVABTC":"0; (0%); 0%","KMDBTC":"0; (0%); 0%","KNCBTC":"0; (0%); 0%","KSMBTC":"0.04004111112168869; (4%); -0.12%","LINABTC":"0; (0%); 0%","LINKBTC":"0; (0%); 0%","LITBTC":"0; (0%); 0%","LOOMBTC":"0; (0%); 0%","LRCBTC":"0.023474373834406356; (2.35%); 0.9%","LSKBTC":"0; (0%); 0%","LTCBTC":"0; (0%); 0%","LTOBTC":"0; (0%); 0%","LUNABTC":"0; (0%); 0%","MANABTC":"0; (0%); 0%","MATICBTC":"0.028787859910857746; (2.88%); 0.53%","MDABTC":"0; (0%); 0%","MDTBTC":"0; (0%); 0%","MIRBTC":"0; (0%); 0%","MITHBTC":"0; (0%); 0%","MKRBTC":"0; (0%); 0%","MTHBTC":"0; (0%); 0%","MTLBTC":"0; (0%); 0%","NANOBTC":"0.015413987612237993; (1.54%); 0.05%","NASBTC":"0.016473648385338754; (1.65%); 1.14%","NAVBTC":"0.005255111554083175; (0.53%); 0.53%","NBSBTC":"0; (0%); 0%","NEARBTC":"0.004636488939155359; (0.46%); 0.46%","NEBLBTC":"0; (0%); 0%","NEOBTC":"0; (0%); 0%","NKNBTC":"0; (0%); 0%","NMRBTC":"0; (0%); -0.25%","NULSBTC":"0; (0%); 0%","NXSBTC":"0; (0%); 0%","OAXBTC":"0; (0%); 0%","OCEANBTC":"0; (0%); 0%","OGBTC":"0.012891826881138345; (1.29%); -0.47%","OGNBTC":"0; (0%); 0%","OMBTC":"0; (0%); 0%","OMGBTC":"0; (0%); 0%","ONEBTC":"0; (0%); 0%","ONGBTC":"0; (0%); 0%","ONTBTC":"0; (0%); 0%","ORNBTC":"0; (0%); 0%","OSTBTC":"0; (0%); 0%","OXTBTC":"0; (0%); 0%","PAXGBTC":"0.1923843158169209; (19.24%); -5.02%","PERLBTC":"0; (0%); 0%","PERPBTC":"0.04233957174254181; (4.23%); -3.29%","PHABTC":"0.02794130576248124; (2.79%); -1.61%","PHBBTC":"0.0030602282863239124; (0.31%); 0.3%","PIVXBTC":"0.05275963495315221; (5.28%); 1.11%","PNTBTC":"0; (0%); 0%","POABTC":"0.0005443556690231861; (0.05%); 0.05%","POLYBTC":"0; (0%); 0%","PONDBTC":"0; (0%); 0%","POWRBTC":"0.009467256313041437; (0.95%); -0.97%","PPTBTC":"0; (0%); 0%","PSGBTC":"0; (0%); -0.49%","QKCBTC":"0; (0%); 0%","QLCBTC":"0.006274001137556872; (0.63%); 0.51%","QSPBTC":"0; (0%); 0%","QTUMBTC":"0; (0%); 0%","RAMPBTC":"0; (0%); 0%","RCNBTC":"0.031284083901154565; (3.13%); 1.22%","RDNBTC":"0; (0%); 0%","REEFBTC":"0.0014215899745690644; (0.14%); -1.39%","RENBTC":"0; (0%); 0%","RENBTCBTC":"0; (0%); 0%","REPBTC":"0.006047822661575887; (0.6%); 0.6%","REQBTC":"0; (0%); 0%","RIFBTC":"0; (0%); 0%","RLCBTC":"0; (0%); 0%","ROSEBTC":"0; (0%); 0%","RSRBTC":"0; (0%); 0%","RUNEBTC":"0.005224936830893978; (0.52%); 0.27%","RVNBTC":"0; (0%); 0%","SANDBTC":"0; (0%); 0%","SCBTC":"0; (0%); 0%","SCRTBTC":"0; (0%); 0%","SFPBTC":"0; (0%); 0%","SKLBTC":"0; (0%); 0%","SKYBTC":"0; (0%); 0%","SNGLSBTC":"0.004504091904144896; (0.45%); -0.2%","SNMBTC":"0; (0%); 0%","SNTBTC":"0; (0%); 0%","SNXBTC":"0.027233693480694418; (2.72%); 0.05%","SOLBTC":"0; (0%); -0.29%","SRMBTC":"0; (0%); 0%","STEEMBTC":"0; (0%); 0%","STMXBTC":"0; (0%); 0%","STORJBTC":"0; (0%); 0%","STPTBTC":"0.007057396462577415; (0.71%); 0.33%","STRAXBTC":"0; (0%); 0%","STXBTC":"0; (0%); 0%","SUNBTC":"0; (0%); 0%","SUPERBTC":"0; (0%); 0%","SUSHIBTC":"0; (0%); 0%","SXPBTC":"0; (0%); 0%","SYSBTC":"0; (0%); 0%","TCTBTC":"0; (0%); 0%","TFUELBTC":"0; (0%); 0%","THETABTC":"0; (0%); 0%","TKOBTC":"0; (0%); 0%","TLMBTC":"0; (0%); 0%","TOMOBTC":"0; (0%); 0%","TRBBTC":"0; (0%); 0%","TROYBTC":"0.0025877179483515915; (0.26%); -0.02%","TRUBTC":"0.009436451870609626; (0.94%); 0.28%","TRXBTC":"0; (0%); 0%","TVKBTC":"0; (0%); 0%","TWTBTC":"0; (0%); 0%","UMABTC":"0; (0%); 0%","UNFIBTC":"0; (0%); 0%","UNIBTC":"0; (0%); 0%","UTKBTC":"0; (0%); 0%","VETBTC":"0; (0%); 0%","VIABTC":"0.002560516321121; (0.26%); 0.26%","VIBBTC":"0; (0%); 0%","VIDTBTC":"0; (0%); 0%","VITEBTC":"0; (0%); 0%","WABIBTC":"0; (0%); 0%","WANBTC":"0; (0%); 0%","WAVESBTC":"0.01123938639809852; (1.12%); 1.12%","WINGBTC":"0; (0%); 0%","WNXMBTC":"0; (0%); -0.24%","WPRBTC":"0.008562388227338822; (0.86%); 0.4%","WRXBTC":"0; (0%); 0%","WTCBTC":"0; (0%); 0%","XEMBTC":"0; (0%); 0%","XLMBTC":"0; (0%); 0%","XMRBTC":"0; (0%); 0%","XRPBTC":"0; (0%); 0%","XTZBTC":"0; (0%); 0%","XVGBTC":"0; (0%); 0%","XVSBTC":"0; (0%); 0%","YFIBTC":"0.013247145316206682; (1.32%); 0.61%","YFIIBTC":"0; (0%); 0%","YOYOBTC":"0.001367735093668989; (0.14%); 0.14%","ZECBTC":"0; (0%); 0%","ZENBTC":"0; (0%); 0%","ZILBTC":"0; (0%); 0%","ZRXBTC":"0; (0%); 0%"},"statisticaT_rendimento_atteso":5.790081608565341,"numerosità_campione":749,"rendimento_atteso":0.00030429578272454593,"deviazione_standard":0.0014383088654013863,"sharpe_ratio":0.21156497748460074}