{"weights":{"AAVEBNB":0,"ADABNB":0.04568371453243329,"ALGOBNB":0,"ALPHABNB":0,"ANKRBNB":0,"ANTBNB":0,"ARBNB":0.01287230524426878,"ARPABNB":0,"ATOMBNB":0,"AVABNB":0,"AVAXBNB":0,"AXSBNB":0,"BAKEBNB":0,"BANDBNB":0,"BATBNB":0,"BCHBNB":0,"BELBNB":0,"BIFIBNB":0.07946874792237978,"BLZBNB":0,"BTTBNB":0,"BURGERBNB":0.0030246516844182015,"CAKEBNB":0.24740741611802491,"CELRBNB":0,"CHRBNB":0,"CHZBNB":0,"COCOSBNB":0,"COSBNB":0.0630759322958608,"COTIBNB":0,"CREAMBNB":0.10267092971026177,"CRVBNB":0.014133515916427142,"CTKBNB":0,"CTSIBNB":0,"DASHBNB":0,"DGBBNB":0,"DIABNB":0,"DOTBNB":0,"EGLDBNB":0,"ENJBNB":0,"EOSBNB":0,"ETCBNB":0,"FETBNB":0,"FILBNB":0,"FIOBNB":0.02016125673071016,"FTMBNB":0,"FTTBNB":0,"HARDBNB":0.02228009265917312,"HBARBNB":0,"HOTBNB":0,"ICPBNB":0,"ICXBNB":0,"INJBNB":0,"IOSTBNB":0,"IOTABNB":0,"IQBNB":0.00473807640467565,"JSTBNB":0,"KAVABNB":0.041441163336552414,"KP3RBNB":0.0007806340402482983,"KSMBNB":0.04908231189833159,"LTCBNB":0,"LUNABNB":0,"MATICBNB":0,"MBLBNB":0,"MFTBNB":0.035602985915221735,"MITHBNB":0.01970040981636676,"MKRBNB":0,"NEARBNB":0,"NEOBNB":0,"NMRBNB":0,"OCEANBNB":0,"OGNBNB":0,"ONEBNB":0,"ONTBNB":0,"PAXGBNB":0.08781855135380705,"PERLBNB":0,"POLSBNB":0,"PROMBNB":0.00958677133089017,"RSRBNB":0,"RUNEBNB":0,"RVNBNB":0,"SANDBNB":0,"SCBNB":0,"SNXBNB":0,"SOLBNB":0,"SPARTABNB":0.031175670558874248,"SRMBNB":0,"STMXBNB":0,"STXBNB":0.009855828347734887,"SUSHIBNB":0,"SWRVBNB":0.014375487971098463,"SXPBNB":0,"THETABNB":0.014368149696373232,"TROYBNB":0,"TRXBNB":0,"UNFIBNB":0,"UNIBNB":0,"VETBNB":0.003774943921179629,"VTHOBNB":0,"WABIBNB":0.01697757975690455,"WANBNB":0,"WAVESBNB":0,"WINBNB":0,"WINGBNB":0,"WNXMBNB":0,"WRXBNB":0.02503341319115951,"WTCBNB":0,"XLMBNB":0,"XMRBNB":0,"XRPBNB":0,"XTZBNB":0,"XVSBNB":0,"YFIBNB":0,"YFIIBNB":0,"ZECBNB":0,"ZENBNB":0.024909459646623874,"ZILBNB":0},"numerosità_campione":528,"expected_return":0.0003534481055329296,"standard_deviation":0.0060975765266591654,"sharpe_ratio":0.057965341474210605}