{"weights":{"ADAETH":0.1549089325881312,"ADXETH":0,"AIONETH":0,"BATETH":0,"BLZETH":0,"BNBETH":0.06861510284639272,"BNTETH":0.018290423966381728,"BQXETH":0.11708568977372179,"BRDETH":0,"CDTETH":0,"CVCETH":0,"DASHETH":0,"DATAETH":0.03007733440001538,"DENTETH":0.006201351135940375,"ELFETH":0,"ENJETH":0,"EOSETH":0,"ETCETH":0.04578779478795213,"FUNETH":0,"GXSETH":0,"HOTETH":0,"ICXETH":0,"IOSTETH":0,"IOTAETH":0,"IOTXETH":0,"KEYETH":0,"KMDETH":0,"KNCETH":0,"LINKETH":0.18008038260262205,"LOOMETH":0,"LRCETH":0,"LSKETH":0,"LTCETH":0,"MANAETH":0.0034583699877633405,"MFTETH":0,"MTLETH":0.03395800279612752,"NANOETH":0,"NASETH":0,"NAVETH":0,"NCASHETH":0.018345126513796314,"NEBLETH":0,"NEOETH":0,"OMGETH":0,"ONTETH":0,"OSTETH":0,"PIVXETH":0,"POWRETH":0,"QKCETH":0,"QLCETH":0,"QSPETH":0,"QTUMETH":0,"REPETH":0,"RLCETH":0,"SCETH":0,"SNTETH":0,"STEEMETH":0,"THETAETH":0.26338641731916845,"TRXETH":0,"VETETH":0.03942424480059188,"VIBETH":0,"WANETH":0,"WAVESETH":0,"XEMETH":0,"XLMETH":0,"XMRETH":0,"XRPETH":0,"XVGETH":0,"ZECETH":0,"ZENETH":0.020380826481395043,"ZILETH":0,"ZRXETH":0},"numerosità_campione":757,"expected_return":0.0029754299940142493,"standard_deviation":0.03239492476411627,"sharpe_ratio":0.09184864652966014}