{"weights":{"1INCHBTC":0,"AAVEBTC":0,"ACMBTC":0.0066348478694711185,"ADABTC":0.05707636498868157,"ADXBTC":0,"AERGOBTC":0,"AGIBTC":0.023955222521722528,"AIONBTC":0,"AKROBTC":0,"ALGOBTC":0,"ALICEBTC":0.05544609025402477,"ALPHABTC":0,"AMBBTC":0,"ANKRBTC":0,"ANTBTC":0,"APPCBTC":0,"ARBTC":0,"ARDRBTC":0,"ARKBTC":0,"ARPABTC":0,"ASTBTC":0,"ATOMBTC":0,"AUCTIONBTC":0.006563698179262987,"AUDIOBTC":0.009475720742525059,"AUTOBTC":0,"AVABTC":0,"AVAXBTC":0.018067015874676455,"AXSBTC":0,"BADGERBTC":0,"BALBTC":0,"BANDBTC":0,"BATBTC":0,"BCDBTC":0,"BCHBTC":0,"BEAMBTC":0,"BELBTC":0,"BLZBTC":0.005357566785766157,"BNBBTC":0,"BNTBTC":0,"BQXBTC":0,"BRDBTC":0,"BTCSTBTC":0.008669766129538637,"BTGBTC":0,"BTSBTC":0,"BZRXBTC":0,"CAKEBTC":0,"CDTBTC":0,"CELOBTC":0.036360244283819426,"CELRBTC":0,"CFXBTC":0,"CHRBTC":0,"CHZBTC":0,"CKBBTC":0,"CNDBTC":0.002146917247449732,"COMPBTC":0,"COSBTC":0,"COTIBTC":0,"CRVBTC":0,"CTKBTC":0,"CTSIBTC":0.010373829844499595,"CTXCBTC":0,"CVCBTC":0,"DASHBTC":0,"DATABTC":0.00916117421609649,"DCRBTC":0,"DEGOBTC":0.011080164738912757,"DGBBTC":0,"DIABTC":0,"DLTBTC":0,"DNTBTC":0.00193759221256567,"DOCKBTC":0.007474041378252021,"DODOBTC":0,"DOGEBTC":0,"DOTBTC":0,"DREPBTC":0,"DUSKBTC":0,"EGLDBTC":0,"ELFBTC":0,"ENJBTC":0,"EOSBTC":0,"EPSBTC":0.002303679309359586,"ETCBTC":0,"ETHBTC":0,"EVXBTC":0,"EZBTC":0,"FETBTC":0,"FILBTC":0,"FIOBTC":0,"FIROBTC":0,"FISBTC":0,"FLMBTC":0,"FORBTC":0,"FORTHBTC":0.017589759492712357,"FRONTBTC":0,"FTMBTC":0,"FTTBTC":0,"FUNBTC":0,"FXSBTC":0,"GASBTC":0,"GLMBTC":0,"GOBTC":0,"GRSBTC":0,"GRTBTC":0,"GTOBTC":0,"GVTBTC":0,"GXSBTC":0,"HARDBTC":0,"HBARBTC":0,"HIVEBTC":0.0030787565715276357,"HNTBTC":0,"ICPBTC":0,"ICXBTC":0,"IDEXBTC":0,"INJBTC":0,"IOSTBTC":0,"IOTABTC":0,"IOTXBTC":0,"IRISBTC":0,"JSTBTC":0,"JUVBTC":0.006150071466443737,"KAVABTC":0,"KMDBTC":0,"KNCBTC":0,"KSMBTC":0.00689295923907083,"LINABTC":0,"LINKBTC":0,"LITBTC":0,"LOOMBTC":0,"LRCBTC":0,"LSKBTC":0,"LTCBTC":0,"LTOBTC":0,"LUNABTC":0,"MANABTC":0,"MATICBTC":0.02269379177691808,"MDABTC":0,"MDTBTC":0.003608314609956197,"MIRBTC":0.04218203474331028,"MITHBTC":0,"MKRBTC":0,"MTHBTC":0,"MTLBTC":0,"NANOBTC":0,"NASBTC":0,"NAVBTC":0,"NBSBTC":0.0033398631597014727,"NEARBTC":0.020282502251232848,"NEBLBTC":0,"NEOBTC":0,"NKNBTC":0,"NMRBTC":0.01663644678006465,"NULSBTC":0,"NXSBTC":0,"OAXBTC":0,"OCEANBTC":0,"OGNBTC":0,"OMBTC":0.006593034994691296,"OMGBTC":0,"ONEBTC":0.02860300996205874,"ONGBTC":0,"ONTBTC":0,"ORNBTC":0,"OSTBTC":0,"OXTBTC":0.0035387898873885464,"PAXGBTC":0.17499915777398148,"PERLBTC":0,"PERPBTC":0.018033715538936027,"PHABTC":0.014425744323985518,"PHBBTC":0.006627188120485533,"PIVXBTC":0.025455951348211513,"PNTBTC":0,"POABTC":0,"POLYBTC":0,"PONDBTC":0,"POWRBTC":0,"PPTBTC":0,"QKCBTC":0,"QLCBTC":0,"QSPBTC":0,"QTUMBTC":0,"RAMPBTC":0,"RCNBTC":0,"RDNBTC":0,"REEFBTC":0,"RENBTC":0,"RENBTCBTC":0.13487981264896484,"REPBTC":0,"REQBTC":0,"RIFBTC":0.0040657168169264376,"RLCBTC":0,"ROSEBTC":0,"RSRBTC":0,"RUNEBTC":0.015819749812401477,"RVNBTC":0,"SANDBTC":0,"SCBTC":0,"SCRTBTC":0,"SFPBTC":0,"SKLBTC":0,"SKYBTC":0,"SNGLSBTC":0.0010943250336497476,"SNMBTC":0,"SNTBTC":0.00902839758399415,"SNXBTC":0,"SOLBTC":0.038981618404136095,"SRMBTC":0.021605676769739256,"STEEMBTC":0,"STMXBTC":0,"STORJBTC":0,"STPTBTC":0,"STRAXBTC":0,"STXBTC":0,"SUNBTC":0,"SUPERBTC":0,"SUSHIBTC":0,"SXPBTC":0,"SYSBTC":0,"TCTBTC":0,"TFUELBTC":0.003034253328026853,"THETABTC":0.004786802957304984,"TKOBTC":0,"TLMBTC":0,"TOMOBTC":0,"TRBBTC":0,"TROYBTC":0,"TRUBTC":0,"TRXBTC":0,"TVKBTC":0,"TWTBTC":0,"UMABTC":0,"UNFIBTC":0,"UNIBTC":0,"UTKBTC":0.005171484434190882,"VETBTC":0,"VIABTC":0,"VIBBTC":0,"VIDTBTC":0,"VITEBTC":0.009062071672134221,"WABIBTC":0,"WANBTC":0,"WAVESBTC":0,"WINGBTC":0.012970223956436645,"WNXMBTC":0,"WPRBTC":0,"WRXBTC":0,"WTCBTC":0,"XEMBTC":0,"XLMBTC":0,"XMRBTC":0,"XRPBTC":0.046684837964793086,"XTZBTC":0,"XVGBTC":0,"XVSBTC":0,"YFIBTC":0,"YFIIBTC":0,"YOYOBTC":0,"ZECBTC":0,"ZENBTC":0,"ZILBTC":0,"ZRXBTC":0},"numerosità_campione":260,"expected_return":0.00020248687519796376,"standard_deviation":0.0012303284135158265,"sharpe_ratio":0.16457953256507396}