{"weights":{"AAVEBNB":0,"ADABNB":0,"ALGOBNB":0,"ALPHABNB":0,"ANKRBNB":0,"ANTBNB":0,"ARPABNB":0,"ATOMBNB":0,"AVABNB":0,"AVAXBNB":0,"AXSBNB":0,"BAKEBNB":0.04445434708394003,"BANDBNB":0,"BATBNB":0,"BCHBNB":0,"BELBNB":0,"BIFIBNB":0,"BLZBNB":0,"BTTBNB":0.03087959520905418,"BURGERBNB":0.01656852409733569,"CAKEBNB":0.33523369233858946,"CELRBNB":0,"CHRBNB":0,"CHZBNB":0,"COCOSBNB":0,"COSBNB":0,"COTIBNB":0,"CREAMBNB":0,"CRVBNB":0,"CTKBNB":0,"CTSIBNB":0.0019077527841283655,"DASHBNB":0,"DGBBNB":0,"DIABNB":0,"DOTBNB":0,"EGLDBNB":0,"ENJBNB":0,"EOSBNB":0,"ETCBNB":0.09354375352961886,"FETBNB":0,"FILBNB":0.06599554621108558,"FIOBNB":0,"FTMBNB":0,"FTTBNB":0,"HARDBNB":0,"HBARBNB":0,"HOTBNB":0,"ICXBNB":0,"INJBNB":0,"IOSTBNB":0,"IOTABNB":0,"IQBNB":0,"JSTBNB":0,"KAVABNB":0,"KP3RBNB":0,"KSMBNB":0,"LTCBNB":0,"LUNABNB":0,"MATICBNB":0.04733669690605472,"MBLBNB":0,"MFTBNB":0,"MITHBNB":0.0003528423995918321,"MKRBNB":0,"NEARBNB":0,"NEOBNB":0,"NMRBNB":0,"OCEANBNB":0,"OGNBNB":0,"ONEBNB":0,"ONTBNB":0,"PAXGBNB":0.11580962683089979,"PERLBNB":0,"PROMBNB":0.0034273848223160264,"RSRBNB":0,"RUNEBNB":0.0575257978529051,"RVNBNB":0,"SANDBNB":0,"SCBNB":0,"SNXBNB":0,"SOLBNB":0.05689621831032761,"SPARTABNB":0.01054521711099492,"SRMBNB":0,"STMXBNB":0,"STXBNB":0,"SUSHIBNB":0,"SWRVBNB":0,"SXPBNB":0,"THETABNB":0,"TROYBNB":0,"TRXBNB":0,"UNFIBNB":0,"UNIBNB":0,"VETBNB":0,"VTHOBNB":0,"WABIBNB":0,"WANBNB":0,"WAVESBNB":0.013705035218163825,"WINBNB":0.00559154662836162,"WINGBNB":0,"WNXMBNB":0.008116826742084676,"WRXBNB":0.034057725230880964,"WTCBNB":0,"XLMBNB":0,"XMRBNB":0,"XRPBNB":0.04172864872107504,"XTZBNB":0,"XVSBNB":0,"YFIBNB":0,"YFIIBNB":0,"ZECBNB":0,"ZENBNB":0.016323221972591978,"ZILBNB":0},"numerosità_campione":515,"expected_return":0.0012585661997574825,"standard_deviation":0.013286808282821513,"sharpe_ratio":0.09472298937169735}