{"weights":{"AAVEETH":0,"ADAETH":0.1687938170828664,"ADXETH":0,"AIONETH":0,"BATETH":0,"BETHETH":0.04988093762901203,"BLZETH":0,"BNBETH":0,"BNTETH":0,"BQXETH":0,"BRDETH":0,"CDTETH":0,"COVERETH":0,"CVCETH":0,"CVPETH":0,"DASHETH":0,"DATAETH":0.1474246055220077,"DENTETH":0,"DEXEETH":0,"DFETH":0,"ELFETH":0,"ENJETH":0,"EOSETH":0,"ETCETH":0.31904600508867653,"EZETH":0,"FIROETH":0,"FRONTETH":0,"FUNETH":0,"GHSTETH":0.06416130750736426,"GLMETH":0,"GRTETH":0,"GXSETH":0.02929259272418153,"HEGICETH":0,"HOTETH":0,"ICXETH":0,"IOSTETH":0,"IOTAETH":0,"IOTXETH":0,"KEYETH":0,"KMDETH":0,"KNCETH":0,"LINKETH":0,"LOOMETH":0,"LRCETH":0,"LSKETH":0,"LTCETH":0,"MANAETH":0,"MFTETH":0,"MTLETH":0,"NANOETH":0.010243345366800105,"NASETH":0,"NAVETH":0,"NCASHETH":0,"NEBLETH":0,"NEOETH":0,"OMGETH":0,"ONTETH":0,"OSTETH":0,"PIVXETH":0,"POWRETH":0,"PROSETH":0,"PUNDIXETH":0,"QKCETH":0,"QLCETH":0,"QSPETH":0,"QTUMETH":0,"RENBTCETH":0,"REPETH":0,"RLCETH":0.10962285017027831,"SCETH":0,"SCRTETH":0,"SLPETH":0.1015345389088131,"SNTETH":0,"STEEMETH":0,"STMXETH":0,"STRAXETH":0,"THETAETH":0,"TRXETH":0,"UFTETH":0,"VETETH":0,"VIBETH":0,"WANETH":0,"WAVESETH":0,"XEMETH":0,"XLMETH":0,"XMRETH":0,"XRPETH":0,"XVGETH":0,"ZECETH":0,"ZENETH":0,"ZILETH":0,"ZRXETH":0},"numerosità_campione":1968,"expected_return":0.00031207146494948253,"standard_deviation":0.00814591019694835,"sharpe_ratio":0.03831020197919588}